{
  "COMMENT": "Static files to load to database. Does nothing if empty",
  "clearAssets":true,
  "files":[
    {
      "filename":"footer.html",
      "filetype":"text/html",
      "base64":false,
      "location":"footer.html"
    },
    {
      "filename":"header.html",
      "filetype":"text/html",
      "base64":false,
      "location":"header.html"
    },
    {
      "filename":"preview.ejs",
      "filetype":"text/html",
      "base64":false,
      "location":"preview.ejs"
    },
    {
      "filename":"pdf.css",
      "filetype":"text/css",
      "base64":false,
      "location":"pdf.css"
    },
    {
      "filename":"font1.otf",
      "filetype":"font/opentype",
      "base64":true,
      "location":"Roboto-Light.txt"
    },
    {
      "filename":"font2.otf",
      "filetype":"font/opentype",
      "base64":true,
      "location":"Roboto-Regular.txt"
    },
    {
      "filename":"font3.otf",
      "filetype":"font/opentype",
      "base64":true,
      "location":"Roboto-Bold.txt"
    }
  ]
}
